gpssnrpy/__init__.py
gpssnrpy/download_orbits.py
gpssnrpy/download_rinex.py
gpssnrpy/gps.py
gpssnrpy/gpssnr.cpython-37m-darwin.so
gpssnrpy/gpssnr_cl.py
gpssnrpy/test.py
gpssnrpy/utils.py
gpssnrpy-0.0.3.dist-info/LICENSE
gpssnrpy-0.0.3.dist-info/METADATA
gpssnrpy-0.0.3.dist-info/WHEEL
gpssnrpy-0.0.3.dist-info/entry_points.txt
gpssnrpy-0.0.3.dist-info/top_level.txt
gpssnrpy-0.0.3.dist-info/RECORD
