Metadata-Version: 2.1
Name: gpssnrpy
Version: 0.0.3
Summary: A GPS/SNR translation software package1 
Home-page: https://github.com/kristinemlarson/gpssnrpy/
Author: Kristine Larson
Author-email: kristinem.larson@gmail.com
License: UNKNOWN
Platform: UNKNOWN
Classifier: Programming Language :: Python :: 3.7
Classifier: License :: OSI Approved :: GNU General Public License v3 (GPLv3)
Requires-Dist: numpy
Requires-Dist: scipy
Requires-Dist: wget
Requires-Dist: matplotlib
